mvc/LICENSE
mvc/__init__.py
mvc/__version.py
mvc/controller.py
mvc/settings.py
mvc/view.py
mvc/adapters/__init__.py
mvc/adapters/abstract_adapter.py
mvc/adapters/adapter_registry.py
mvc/adapters/dummy_adapter.py
mvc/adapters/metaclasses.py
mvc/adapters/model_adapter.py
mvc/adapters/gtk_support/__init__.py
mvc/adapters/gtk_support/_gtk_color_utils.py
mvc/adapters/gtk_support/adjustment_adapter.py
mvc/adapters/gtk_support/arrow_adapter.py
mvc/adapters/gtk_support/basic.py
mvc/adapters/gtk_support/check_menu_item_adapter.py
mvc/adapters/gtk_support/color_button_adapter.py
mvc/adapters/gtk_support/color_selection_adapter.py
mvc/adapters/gtk_support/combo_box_adapter.py
mvc/adapters/gtk_support/entry_adapter.py
mvc/adapters/gtk_support/expander_adapter.py
mvc/adapters/gtk_support/file_chooser_adapter.py
mvc/adapters/gtk_support/float_entry_adapter.py
mvc/adapters/gtk_support/label_adapter.py
mvc/adapters/gtk_support/link_button_adapter.py
mvc/adapters/gtk_support/scale_adapter.py
mvc/adapters/gtk_support/text_view_adapter.py
mvc/adapters/gtk_support/toggle_button_adapter.py
mvc/adapters/gtk_support/toolkit_functions.py
mvc/adapters/gtk_support/tree_view_adapters.py
mvc/adapters/gtk_support/dialogs/__init__.py
mvc/adapters/gtk_support/dialogs/dialog_factory.py
mvc/adapters/gtk_support/dialogs/file_chooser_dialog.py
mvc/adapters/gtk_support/dialogs/message_dialog.py
mvc/adapters/gtk_support/dialogs/utils.py
mvc/adapters/gtk_support/treemodels/__init__.py
mvc/adapters/gtk_support/treemodels/base_models.py
mvc/adapters/gtk_support/treemodels/generic_tree_model.py
mvc/adapters/gtk_support/treemodels/object_list_store.py
mvc/adapters/gtk_support/treemodels/object_tree_store.py
mvc/adapters/gtk_support/treemodels/utils.py
mvc/adapters/gtk_support/treemodels/xy_list_store.py
mvc/adapters/gtk_support/widgets/__init__.py
mvc/adapters/gtk_support/widgets/scale_entry.py
mvc/adapters/gtk_support/widgets/threaded_task_box.py
mvc/models/__init__.py
mvc/models/base.py
PyXRD-0.8.4.dist-info/LICENSE
PyXRD-0.8.4.dist-info/METADATA
PyXRD-0.8.4.dist-info/WHEEL
PyXRD-0.8.4.dist-info/top_level.txt
PyXRD-0.8.4.dist-info/RECORD
