Metadata-Version: 2.1
Name: PyXRD
Version: 0.8.4
Summary: PyXRD is a python implementation of the matrix algorithm developed for the X-ray diffraction analysis of disordered lamellar structures
Home-page: http://github.org/mathijs-dumon/PyXRD
Author: Mathijs Dumon
Author-email: mathijs.dumon@gmail.com
License: BSD
Keywords: XRD disorder mixed-layers
Platform: UNKNOWN
Classifier: Development Status :: 4 - Beta
Classifier: Operating System :: Microsoft :: Windows
Classifier: Operating System :: POSIX :: Linux
Classifier: Programming Language :: Python :: 3.4
Classifier: Environment :: Win32 (MS Windows)
Classifier: Environment :: X11 Applications :: Gnome
Classifier: Environment :: X11 Applications :: GTK
Classifier: Intended Audience :: End Users/Desktop
Classifier: Intended Audience :: Science/Research
Classifier: Topic :: Utilities
Classifier: Topic :: Scientific/Engineering
Classifier: Topic :: Scientific/Engineering :: Visualization
Classifier: Natural Language :: English
Classifier: License :: OSI Approved :: BSD License
Requires-Dist: setuptools
Requires-Dist: numpy (>=1.11)
Requires-Dist: scipy (>=1.1.0)
Requires-Dist: matplotlib (>=2.2.2)
Requires-Dist: Pyro4 (>=4.41)
Requires-Dist: deap (>=1.0.1)
Requires-Dist: cairocffi
Requires-Dist: pygobject (>=3.20)
